{
  "hash": "47916fd1",
  "configHash": "2b924181",
  "lockfileHash": "d296abfe",
  "browserHash": "85531d53",
  "optimized": {
    "react": {
      "src": "../../node_modules/react/index.js",
      "file": "react.js",
      "fileHash": "4c0835af",
      "needsInterop": true
    },
    "react-router-dom": {
      "src": "../../node_modules/react-router-dom/dist/index.js",
      "file": "react-router-dom.js",
      "fileHash": "d965037c",
      "needsInterop": false
    },
    "lucide-react": {
      "src": "../../node_modules/lucide-react/dist/esm/lucide-react.js",
      "file": "lucide-react.js",
      "fileHash": "ad35fac3",
      "needsInterop": false
    },
    "react-hot-toast": {
      "src": "../../node_modules/react-hot-toast/dist/index.mjs",
      "file": "react-hot-toast.js",
      "fileHash": "9ac6d369",
      "needsInterop": false
    },
    "axios": {
      "src": "../../node_modules/axios/index.js",
      "file": "axios.js",
      "fileHash": "a5c32c1d",
      "needsInterop": false
    },
    "zustand": {
      "src": "../../node_modules/zustand/esm/index.mjs",
      "file": "zustand.js",
      "fileHash": "10200825",
      "needsInterop": false
    },
    "zustand/middleware": {
      "src": "../../node_modules/zustand/esm/middleware.mjs",
      "file": "zustand_middleware.js",
      "fileHash": "24b38e0c",
      "needsInterop": false
    },
    "react-dom/client": {
      "src": "../../node_modules/react-dom/client.js",
      "file": "react-dom_client.js",
      "fileHash": "f4b3ab48",
      "needsInterop": true
    },
    "date-fns": {
      "src": "../../node_modules/date-fns/index.mjs",
      "file": "date-fns.js",
      "fileHash": "bfcef1ce",
      "needsInterop": false
    },
    "recharts": {
      "src": "../../node_modules/recharts/es6/index.js",
      "file": "recharts.js",
      "fileHash": "acc31f73",
      "needsInterop": false
    }
  },
  "chunks": {
    "chunk-JMVEG3FK": {
      "file": "chunk-JMVEG3FK.js"
    },
    "chunk-TWJRYSII": {
      "file": "chunk-TWJRYSII.js"
    },
    "chunk-DC5AMYBS": {
      "file": "chunk-DC5AMYBS.js"
    }
  }
}